verify/__init__.py
verify/base.py
verify/__meta__.py
verify/logic.py
verify/runners.py
verify/numbers.py
verify/types.py
verify/equality.py
verify/containers.py
verify-1.1.1.dist-info/top_level.txt
verify-1.1.1.dist-info/METADATA
verify-1.1.1.dist-info/DESCRIPTION.rst
verify-1.1.1.dist-info/metadata.json
verify-1.1.1.dist-info/WHEEL
verify-1.1.1.dist-info/RECORD
